README.txt
setup.py
lru_cacher/__init__.py
lru_cacher/lru_cacher.py
lru_cacher.egg-info/PKG-INFO
lru_cacher.egg-info/SOURCES.txt
lru_cacher.egg-info/dependency_links.txt
lru_cacher.egg-info/requires.txt
lru_cacher.egg-info/top_level.txt