Metadata-Version: 1.1
Name: lru-cacher
Version: 1.0.0
Summary: Least Recently used Cache (LRU Cache) in Python
Home-page: https://github.com/AWNystrom/lru_cache
Author: Andrew Nystrom
Author-email: AWNystrom@gmail.com
License: Apache 2.0
Keywords: lru,cache,least,recently,used
Platform: UNKNOWN
Classifier: Programming Language :: Python
Classifier: Programming Language :: Python :: 2.7
Classifier: Programming Language :: Python :: 2
Classifier: License :: OSI Approved :: Apache Software License
Classifier: Operating System :: OS Independent
Classifier: Development Status :: 4 - Beta
Classifier: Intended Audience :: Developers
